tests/__init__.py
tests/conftest.py
tests/test_errors.py
tests/test_exceptions.py
tests/test_send.py
tests/test_validation.py
textfully/__init__.py
textfully/exceptions.py
textfully/version.py
textfully-0.1.2.dist-info/LICENSE
textfully-0.1.2.dist-info/METADATA
textfully-0.1.2.dist-info/WHEEL
textfully-0.1.2.dist-info/top_level.txt
textfully-0.1.2.dist-info/RECORD
