Metadata-Version: 2.1
Name: textfully
Version: 0.1.2
Summary: Textfully Python SDK
Home-page: https://github.com/gtfol/textfully-python
Author: Textfully
Author-email: textfully@gtfol.inc
License: MIT
Classifier: Programming Language :: Python :: 3
Classifier: License :: OSI Approved :: MIT License
Classifier: Operating System :: OS Independent
Requires-Python: >=3.7
License-File: LICENSE
Requires-Dist: requests>=2.25.0
